Metadata-Version: 1.1
Name: pystatsd
Version: 0.1.9
Summary: pystatsd is a client for Etsy's statsd server, a front end/proxy for the Graphite stats collection and graphing server.
Home-page: https://github.com/sivy/py-statsd
Author: Steve Ivy
Author-email: steveivy@gmail.com
License: BSD
Platform: UNKNOWN
Classifier: License :: OSI Approved :: BSD License
Requires: argparse
